skys_llc_auth/__init__.py
skys_llc_auth/cryptography.py
skys_llc_auth/databases.py
skys_llc_auth/exceptions.py
skys_llc_auth/kafka_manager.py
skys_llc_auth/microservices.py
skys_llc_auth/models.py
skys_llc_auth/schemas.py
skys_llc_auth/token_validation.py
skys_llc_auth/utils.py
skys_llc_auth-0.1.37.dist-info/LICENSE
skys_llc_auth-0.1.37.dist-info/METADATA
skys_llc_auth-0.1.37.dist-info/WHEEL
skys_llc_auth-0.1.37.dist-info/top_level.txt
skys_llc_auth-0.1.37.dist-info/RECORD
