Metadata-Version: 2.1
Name: skys_llc_auth
Version: 0.1.37
Summary: Библиотека для работы с Jwt_token
Author: skys_llc
Author-email: skys.llc@ya.ru
Classifier: Programming Language :: Python :: 3
Classifier: License :: OSI Approved :: MIT License
Classifier: Operating System :: OS Independent
Requires-Python: >=3.10
License-File: LICENSE
Requires-Dist: PyJWT
Requires-Dist: cryptography
Requires-Dist: fastapi
Requires-Dist: alembic
Requires-Dist: sqlalchemy
Requires-Dist: asyncpg
Requires-Dist: aiokafka
